yolov9/LICENSE.md
yolov9/README.md
yolov9/__init__.py
yolov9/benchmarks.py
yolov9/detect.py
yolov9/detect_dual.py
yolov9/export.py
yolov9/hubconf.py
yolov9/load.py
yolov9/requirements.txt
yolov9/train.py
yolov9/train_dual.py
yolov9/train_triple.py
yolov9/val.py
yolov9/val_dual.py
yolov9/val_triple.py
yolov9/classify/__init__.py
yolov9/classify/predict.py
yolov9/classify/train.py
yolov9/classify/val.py
yolov9/models/__init__.py
yolov9/models/common.py
yolov9/models/experimental.py
yolov9/models/tf.py
yolov9/models/yolo.py
yolov9/panoptic/__init__.py
yolov9/panoptic/predict.py
yolov9/panoptic/train.py
yolov9/panoptic/val.py
yolov9/segment/__init__.py
yolov9/segment/predict.py
yolov9/segment/train.py
yolov9/segment/train_dual.py
yolov9/segment/val.py
yolov9/segment/val_dual.py
yolov9/utils/__init__.py
yolov9/utils/activations.py
yolov9/utils/augmentations.py
yolov9/utils/autoanchor.py
yolov9/utils/autobatch.py
yolov9/utils/callbacks.py
yolov9/utils/coco_utils.py
yolov9/utils/dataloaders.py
yolov9/utils/downloads.py
yolov9/utils/general.py
yolov9/utils/lion.py
yolov9/utils/loss.py
yolov9/utils/loss_tal.py
yolov9/utils/loss_tal_dual.py
yolov9/utils/loss_tal_triple.py
yolov9/utils/metrics.py
yolov9/utils/plots.py
yolov9/utils/torch_utils.py
yolov9/utils/triton.py
yolov9/utils/loggers/__init__.py
yolov9/utils/loggers/clearml/__init__.py
yolov9/utils/loggers/clearml/clearml_utils.py
yolov9/utils/loggers/clearml/hpo.py
yolov9/utils/loggers/comet/__init__.py
yolov9/utils/loggers/comet/comet_utils.py
yolov9/utils/loggers/comet/hpo.py
yolov9/utils/loggers/wandb/__init__.py
yolov9/utils/loggers/wandb/log_dataset.py
yolov9/utils/loggers/wandb/sweep.py
yolov9/utils/loggers/wandb/wandb_utils.py
yolov9/utils/panoptic/__init__.py
yolov9/utils/panoptic/augmentations.py
yolov9/utils/panoptic/dataloaders.py
yolov9/utils/panoptic/general.py
yolov9/utils/panoptic/loss.py
yolov9/utils/panoptic/loss_tal.py
yolov9/utils/panoptic/metrics.py
yolov9/utils/panoptic/plots.py
yolov9py-1.1.0.dist-info/LICENSE.md
yolov9py-1.1.0.dist-info/METADATA
yolov9py-1.1.0.dist-info/WHEEL
yolov9py-1.1.0.dist-info/top_level.txt
yolov9py-1.1.0.dist-info/RECORD
