Metadata-Version: 2.1
Name: yolov9py
Version: 1.1.0
Summary: YOLOv9: Learning What You Want to Learn Using Programmable Gradient Information.
License: GNU GENERAL PUBLIC LICENSE
Project-URL: repository, https://github.com/WongKinYiu/yolov9
Keywords: deep-learning,pytorch,vision,object-detection,semantic-segmentation,instance-segmentation,panoptic-segmentation,pose-estimation
Classifier: Development Status :: 5 - Production/Stable
Classifier: Operating System :: OS Independent
Classifier: Intended Audience :: Science/Research
Classifier: Programming Language :: Python :: 3
Classifier: License :: OSI Approved :: GNU General Public License v3 (GPLv3)  
Classifier: Topic :: Scientific/Engineering :: Artificial Intelligence
Requires-Python: >=3.10
License-File: LICENSE.md
Requires-Dist: gitpython
Requires-Dist: ipython
Requires-Dist: matplotlib >=3.2.2
Requires-Dist: numpy >=1.18.5
Requires-Dist: opencv-python >=4.1.1
Requires-Dist: Pillow >=7.1.2
Requires-Dist: psutil
Requires-Dist: PyYAML >=5.3.1
Requires-Dist: requests >=2.23.0
Requires-Dist: scipy >=1.4.1
Requires-Dist: thop >=0.1.1
Requires-Dist: torch >=1.7.0
Requires-Dist: torchvision >=0.8.1
Requires-Dist: tqdm >=4.64.0
Requires-Dist: tensorboard >=2.4.1
Requires-Dist: pandas >=1.1.4
Requires-Dist: seaborn >=0.11.0
Requires-Dist: albumentations >=1.0.3
Requires-Dist: pycocotools >=2.0
